[
  {
    "title": "Mưa",
    "file": "01mua.mp3"
  },
  {
    "title": "Dấu mưa",
    "file": "02daumua.mp3"
  },
  {
    "title": "Tương tư trong mưa",
    "file": "07tuongtutrongmua.mp3"
  },

  {
    "title": "Chiều mưa xứ dừa",
    "file": "08chieumuaxudua.mp3"
  },

  {
    "title": "Cafe đắng và mưa",
    "file": "05cafedangvamua.mp3"
  },

  {
    "title": "Đường vắng chiều mưa",
    "file": "06duongvangchieumua.mp3"
  },

  {
    "title": "Em về kẻo trời mưa",
    "file": "09emvekheotromua.mp3"
  },

  {
    "title": "Mối tình chiều mưa bay",
    "file": "10moitinhchieumuabay.mp3"
  }


]